AUTHORS
LICENSE
MANIFEST.in
README.rst
RELEASE-VERSION
setup.py
docs/core.rst
docs/pcap.rst
docs/pcap_from_libpcap_readme.rst
docs/pcapquery.rst
docs/toc.rst
docs/tutorial.rst
gitpy_versioning/__init__.py
steelscript/__init__.pxd
steelscript/__init__.py
steelscript.packets.egg-info/PKG-INFO
steelscript.packets.egg-info/SOURCES.txt
steelscript.packets.egg-info/dependency_links.txt
steelscript.packets.egg-info/entry_points.txt
steelscript.packets.egg-info/namespace_packages.txt
steelscript.packets.egg-info/not-zip-safe
steelscript.packets.egg-info/requires.txt
steelscript.packets.egg-info/top_level.txt
steelscript/packets/__init__.pxd
steelscript/packets/__init__.py
steelscript/packets/commands/__init__.py
steelscript/packets/commands/netflow_player.py
steelscript/packets/core/__init__.pxd
steelscript/packets/core/__init__.py
steelscript/packets/core/inetpkt.c
steelscript/packets/core/inetpkt.pxd
steelscript/packets/core/inetpkt.pyx
steelscript/packets/core/pcap.c
steelscript/packets/core/pcap.pxd
steelscript/packets/core/pcap.pyx
steelscript/packets/protos/__init__.py
steelscript/packets/protos/dns.c
steelscript/packets/protos/dns.pxd
steelscript/packets/protos/dns.pyx
steelscript/packets/protos/dns_purepy.py
steelscript/packets/query/__init__.pxd
steelscript/packets/query/__init__.py
steelscript/packets/query/pcap_query.c
steelscript/packets/query/pcap_query.pxd
steelscript/packets/query/pcap_query.pyx
test/test_packets.py