Metadata-Version: 1.1
Name: steelscript.packets
Version: 2.0
Summary: Base PCAP and inet packet classes.
Home-page: http://pythonhosted.org/steelscript
Author: Riverbed Technology
Author-email: eng-github@riverbed.com
License: MIT
Platform: Linux
Platform: Mac OS
Platform: Windows
Classifier: Intended Audience :: Developers
Classifier: Intended Audience :: Information Technology
Classifier: Intended Audience :: System Administrators
Classifier: License :: OSI Approved :: MIT License
Classifier: Programming Language :: Python :: 3.5
Classifier: Programming Language :: Python :: 3.6
Classifier: Programming Language :: Python :: 3.7
Classifier: Topic :: System :: Networking
